cornice/__init__.py
cornice/cors.py
cornice/errors.py
cornice/pyramidhook.py
cornice/renderer.py
cornice/resource.py
cornice/service.py
cornice/util.py
cornice/validators/__init__.py
cornice/validators/_colander.py
cornice/validators/_marshmallow.py
cornice-6.1.0.dist-info/LICENSE
cornice-6.1.0.dist-info/METADATA
cornice-6.1.0.dist-info/WHEEL
cornice-6.1.0.dist-info/top_level.txt
cornice-6.1.0.dist-info/RECORD
