Metadata-Version: 2.1
Name: cornice
Version: 6.1.0
Summary: Define Web Services in Pyramid.
Author-email: Mozilla Services <services-dev@mozilla.org>
License: This Source Code Form is subject to the terms of the Mozilla Public License, v.
Project-URL: Repository, https://github.com/Cornices/cornice
Keywords: web pyramid pylons
Classifier: Programming Language :: Python
Classifier: Programming Language :: Python :: 3
Classifier: Programming Language :: Python :: Implementation :: CPython
Classifier: Topic :: Internet :: WWW/HTTP
Classifier: Topic :: Internet :: WWW/HTTP :: WSGI :: Application
Classifier: Framework :: Pylons
Classifier: License :: OSI Approved :: Mozilla Public License 2.0 (MPL 2.0)
License-File: LICENSE
Requires-Dist: pyramid<3,>=1.7
Provides-Extra: dev
Requires-Dist: ruff; extra == "dev"
Requires-Dist: pytest<9; extra == "dev"
Requires-Dist: pytest-cache<2; extra == "dev"
Requires-Dist: pytest-cov<5; extra == "dev"
Requires-Dist: WebTest<4; extra == "dev"
Requires-Dist: marshmallow<4; extra == "dev"
Requires-Dist: colander<3; extra == "dev"
